Metadata-Version: 1.1
Name: mommygae
Version: 1.0
Summary: Automate the creation of models on ndb from Google App Engine
Home-page: https://github.com/renzon/mommy-gae
Author: Renzo Nuccitelli
Author-email: renzo.n@gmail.com
License: BSD
Platform: UNKNOWN
Classifier: Development Status :: 5 - Production/Stable
Classifier: Environment :: Web Environment
Classifier: Intended Audience :: Developers
Classifier: License :: OSI Approved :: BSD License
Classifier: Operating System :: OS Independent
Classifier: Programming Language :: Python
Classifier: Framework :: Paste
